tox_envfile/__init__.py
tox_envfile/plugin.py
tox_envfile-0.0.8.dist-info/LICENSE
tox_envfile-0.0.8.dist-info/METADATA
tox_envfile-0.0.8.dist-info/WHEEL
tox_envfile-0.0.8.dist-info/entry_points.txt
tox_envfile-0.0.8.dist-info/top_level.txt
tox_envfile-0.0.8.dist-info/RECORD
