Metadata-Version: 2.2
Name: tox-envfile
Version: 0.0.8
Summary: Load env files in your tox envs.
Project-URL: Repository, https://github.com/hypothesis/tox-envfile
Project-URL: Issues, https://github.com/hypothesis/tox-envfile/issues
Project-URL: Changelog, https://github.com/hypothesis/tox-envfile/releases
Classifier: Programming Language :: Python :: 3
Classifier: License :: OSI Approved :: BSD License
Classifier: Intended Audience :: Developers
Requires-Python: >=3.9
License-File: LICENSE
Requires-Dist: python-dotenv
